tasks/__init__.py
tasks/docker.py
tasks/py.py
testdocker/__init__.py
testdocker/commands.py
testdocker/mixins.py
testdocker/objects.py
testdocker/util.py
testdocker/cli/__init__.py
testdocker/cli/main.py
testdocker/cli/template/requirements.txt
testdocker/cli/template/run
testdocker/cli/template/tests.py
testdocker/cli/template/vars.env
testdocker-0.2.6.dist-info/DESCRIPTION.rst
testdocker-0.2.6.dist-info/METADATA
testdocker-0.2.6.dist-info/RECORD
testdocker-0.2.6.dist-info/WHEEL
testdocker-0.2.6.dist-info/entry_points.txt
testdocker-0.2.6.dist-info/metadata.json
testdocker-0.2.6.dist-info/top_level.txt
