Metadata-Version: 2.0
Name: testdocker
Version: 0.2.6
Summary: Testing for docker containers
Home-page: https://github.com/joeblackwaslike/testdocker
Author: Joe Black
Author-email: joeblack949@gmail.com
License: Apache 2.0
Download-URL: https://github.com/joeblackwaslike/testdocker/tarball/0.2.6
Keywords: docker,docker-compose,testing
Platform: UNKNOWN
Classifier: Development Status :: 3 - Alpha
Classifier: Intended Audience :: Developers
Classifier: Operating System :: OS Independent
Classifier: Natural Language :: English
Classifier: License :: OSI Approved :: Apache Software License
Classifier: Programming Language :: Python :: 3 :: Only
Requires-Dist: PyYAML
Requires-Dist: colour-runner
Requires-Dist: docker
Requires-Dist: requests
